seallib/__init__.py
seallib/eyler/__init__.py
seallib/eyler/eyler.py
seallib/eyler/eyler_func.py
seallib/eyler/func_eyler.py
seallib/graphs/__init__.py
seallib/graphs/deykstra.py
seallib/graphs/deykstra_alg.py
seallib-0.5.dist-info/licenses/LICENSE
seallib-0.5.dist-info/METADATA
seallib-0.5.dist-info/WHEEL
seallib-0.5.dist-info/top_level.txt
seallib-0.5.dist-info/RECORD
