Metadata-Version: 2.4
Name: seallib
Version: 0.5
Summary: Учебная библиотека
Author: Yaroslav Merkulov
Author-email: 1132242913@rudn.ru
License: MIT
Keywords: example library python
Classifier: Programming Language :: Python :: 3
Classifier: License :: OSI Approved :: MIT License
Classifier: Operating System :: OS Independent
License-File: LICENSE
Dynamic: author
Dynamic: author-email
Dynamic: classifier
Dynamic: description
Dynamic: description-content-type
Dynamic: keywords
Dynamic: license
Dynamic: license-file
Dynamic: summary
